django_aws_secrets_env_setup/__init__.py
django_aws_secrets_env_setup-0.3.dist-info/LICENSE
django_aws_secrets_env_setup-0.3.dist-info/METADATA
django_aws_secrets_env_setup-0.3.dist-info/WHEEL
django_aws_secrets_env_setup-0.3.dist-info/top_level.txt
django_aws_secrets_env_setup-0.3.dist-info/RECORD
