Metadata-Version: 2.1
Name: django-aws-secrets-env-setup
Version: 0.3
Summary: A helper function for setting environment variables from AWS secret manager
Home-page: https://github.com/Lenders-Cooperative/django-aws-secrets-env-setup
Author: Levi Anderson
Classifier: Programming Language :: Python :: 3
Classifier: License :: OSI Approved :: BSD License
Classifier: Operating System :: OS Independent
Requires-Python: >=3.6
License-File: LICENSE
Requires-Dist: boto3 (>=1.15.5)
